zadnegoale/__init__.py
zadnegoale/const.py
zadnegoale/model.py
zadnegoale/py.typed
zadnegoale-0.7.0.dist-info/LICENSE
zadnegoale-0.7.0.dist-info/METADATA
zadnegoale-0.7.0.dist-info/WHEEL
zadnegoale-0.7.0.dist-info/top_level.txt
zadnegoale-0.7.0.dist-info/zip-safe
zadnegoale-0.7.0.dist-info/RECORD
