Metadata-Version: 2.1
Name: zadnegoale
Version: 0.7.0
Summary: Python wrapper for getting allergen concentration data from Żadnego Ale servers.
Home-page: https://github.com/bieniu/zadnegoale
Author: Maciej Bieniek
License: Apache-2.0 License
Platform: any
Classifier: Development Status :: 5 - Production/Stable
Classifier: License :: OSI Approved :: Apache Software License
Classifier: Operating System :: OS Independent
Classifier: Programming Language :: Python
Classifier: Programming Language :: Python :: 3
Classifier: Programming Language :: Python :: 3.9
Classifier: Programming Language :: Python :: 3.10
Classifier: Programming Language :: Python :: 3.11
Classifier: Programming Language :: Python :: 3 :: Only
Classifier: Typing :: Typed
Requires-Python: >=3.9
License-File: LICENSE
Requires-Dist: aiohttp (>3)
Requires-Dist: dacite
